prompthub/__init__.py
prompthub/prompt.py
prompthub_py-3.0.1.dist-info/LICENSE
prompthub_py-3.0.1.dist-info/METADATA
prompthub_py-3.0.1.dist-info/WHEEL
prompthub_py-3.0.1.dist-info/RECORD
